odoo/addons/account_portal_hide_invoice/README.rst
odoo/addons/account_portal_hide_invoice/__init__.py
odoo/addons/account_portal_hide_invoice/__manifest__.py
odoo/addons/account_portal_hide_invoice/i18n/account_portal_hide_invoice.pot
odoo/addons/account_portal_hide_invoice/i18n/es.po
odoo/addons/account_portal_hide_invoice/readme/CONTRIBUTORS.rst
odoo/addons/account_portal_hide_invoice/readme/CREDITS.rst
odoo/addons/account_portal_hide_invoice/readme/DESCRIPTION.rst
odoo/addons/account_portal_hide_invoice/static/description/icon.png
odoo/addons/account_portal_hide_invoice/static/description/index.html
odoo/addons/account_portal_hide_invoice/views/account_portal_templates.xml
odoo12_addon_account_portal_hide_invoice-12.0.1.0.0.99.dev6.dist-info/METADATA
odoo12_addon_account_portal_hide_invoice-12.0.1.0.0.99.dev6.dist-info/WHEEL
odoo12_addon_account_portal_hide_invoice-12.0.1.0.0.99.dev6.dist-info/top_level.txt
odoo12_addon_account_portal_hide_invoice-12.0.1.0.0.99.dev6.dist-info/RECORD
